mixtrain/__init__.py
mixtrain/client.py
mixtrain/datasets.py
mixtrain/evaluations.py
mixtrain/files.py
mixtrain/helpers.py
mixtrain/models.py
mixtrain/result.py
mixtrain/routers.py
mixtrain/types.py
mixtrain/workflows.py
mixtrain/cli/__init__.py
mixtrain/cli/dataset.py
mixtrain/cli/file.py
mixtrain/cli/model.py
mixtrain/cli/provider.py
mixtrain/cli/router.py
mixtrain/cli/secret.py
mixtrain/cli/update.py
mixtrain/cli/utils.py
mixtrain/cli/workflow.py
mixtrain/routing/__init__.py
mixtrain/routing/builder.py
mixtrain/routing/conditions.py
mixtrain/routing/engine.py
mixtrain/routing/exceptions.py
mixtrain/routing/models.py
mixtrain/routing/strategies.py
mixtrain/routing/validator.py
mixtrain/utils/__init__.py
mixtrain/utils/auth.py
mixtrain/utils/config.py
mixtrain-0.1.32.dist-info/METADATA
mixtrain-0.1.32.dist-info/WHEEL
mixtrain-0.1.32.dist-info/entry_points.txt
mixtrain-0.1.32.dist-info/RECORD
