Metadata-Version: 2.4
Name: mixtrain
Version: 0.1.32
Summary: Mixtrain SDK and CLI
Author-email: Dharmesh Kakadia <dharmesh.kakadia@gmail.com>
Requires-Python: >=3.10
Requires-Dist: duckdb>=1.3.2
Requires-Dist: httpx>=0.28.1
Requires-Dist: packaging>=21.0
Requires-Dist: polars>=1.32.0
Requires-Dist: pydantic>=2.10.6
Requires-Dist: pyiceberg[pyarrow,sql-postgres]>=0.9.1
Requires-Dist: rich>=13.0.0
Requires-Dist: textual>=5.0.1
Requires-Dist: typer>=0.16.0
Provides-Extra: test
Requires-Dist: pytest-asyncio>=0.21.0; extra == 'test'
Requires-Dist: pytest-httpx>=0.21.0; extra == 'test'
Requires-Dist: pytest-mock>=3.10.0; extra == 'test'
Requires-Dist: pytest>=7.0.0; extra == 'test'
